MANIFEST.in
README.txt
setup.cfg
setup.py
medialog/__init__.py
medialog.boardfile.egg-info/PKG-INFO
medialog.boardfile.egg-info/SOURCES.txt
medialog.boardfile.egg-info/dependency_links.txt
medialog.boardfile.egg-info/entry_points.txt
medialog.boardfile.egg-info/namespace_packages.txt
medialog.boardfile.egg-info/not-zip-safe
medialog.boardfile.egg-info/paster_plugins.txt
medialog.boardfile.egg-info/requires.txt
medialog.boardfile.egg-info/top_level.txt
medialog/boardfile/README.txt
medialog/boardfile/__init__.py
medialog/boardfile/config.py
medialog/boardfile/configure.zcml
medialog/boardfile/browser/__init__.py
medialog/boardfile/browser/boardfileturner.pt
medialog/boardfile/browser/boardfileview.pt
medialog/boardfile/browser/boardfileview.py
medialog/boardfile/browser/configure.zcml
medialog/boardfile/browser/events.py
medialog/boardfile/browser/interfaces.py
medialog/boardfile/browser/publicationrequestview.pt
medialog/boardfile/browser/publicationrequestview.py
medialog/boardfile/browser/publicationturner.pt
medialog/boardfile/browser/publicationview.pt
medialog/boardfile/browser/publicationview.py
medialog/boardfile/browser/views.py
medialog/boardfile/content/__init__.py
medialog/boardfile/content/boardfile.py
medialog/boardfile/content/configure.zcml
medialog/boardfile/content/publication.py
medialog/boardfile/content/publicationrequest.py
medialog/boardfile/interfaces/__init__.py
medialog/boardfile/interfaces/boardfile.py
medialog/boardfile/interfaces/publication.py
medialog/boardfile/interfaces/publicationrequest.py
medialog/boardfile/portlets/__init__.py
medialog/boardfile/portlets/configure.zcml
medialog/boardfile/profiles/contenttypes/catalog.xml
medialog/boardfile/profiles/contenttypes/factorytool.xml
medialog/boardfile/profiles/contenttypes/metadata.xml
medialog/boardfile/profiles/contenttypes/portal_atct.xml
medialog/boardfile/profiles/contenttypes/types.xml
medialog/boardfile/profiles/contenttypes/types/Boardfile.xml
medialog/boardfile/profiles/contenttypes/types/Publication.xml
medialog/boardfile/profiles/contenttypes/types/PublicationRequest.xml
medialog/boardfile/profiles/default/catalog.xml
medialog/boardfile/profiles/default/factorytool.xml
medialog/boardfile/profiles/default/metadata.xml
medialog/boardfile/profiles/default/portal_atct.xml
medialog/boardfile/profiles/default/portlets.xml
