Metadata-Version: 1.1
Name: medialog.boardfile
Version: 1.6.2
Summary: Boardfile content type
Home-page: http://medialog.no
Author: Espen Moe-Nilssen
Author-email: espen@medialog.no
License: GPL
Platform: UNKNOWN
Classifier: Framework :: Plone
Classifier: Intended Audience :: Developers
Classifier: License :: OSI Approved :: GNU General Public License (GPL)
